setup.cfg
setup.py
zmqdump
zmqdump.py
test/test_argparse.py
test/test_socket.py
zmqdump.egg-info/PKG-INFO
zmqdump.egg-info/SOURCES.txt
zmqdump.egg-info/dependency_links.txt
zmqdump.egg-info/requires.txt
zmqdump.egg-info/top_level.txt