Metadata-Version: 1.0
Name: zmqdump
Version: 0.1
Summary: Dump messages on zeromq socket.
Home-page: http://github.com/HeinrichHartmann/zmqdump
Author: Heinrich Hartmann
Author-email: derhein@gmail.com
License: UNKNOWN
Platform: UNKNOWN
